setup.py
kerutils/__init__.py
kerutils/dlutils.py
kerutils/imgutils.py
kerutils/prob.py
kerutils.egg-info/PKG-INFO
kerutils.egg-info/SOURCES.txt
kerutils.egg-info/dependency_links.txt
kerutils.egg-info/not-zip-safe
kerutils.egg-info/requires.txt
kerutils.egg-info/top_level.txt