Metadata-Version: 1.0
Name: kerutils
Version: 2.21
Summary: Keras utilities
Home-page: http://github.com/samyzaf/kerutils
Author: Samy Zafrany
Author-email: admin@samyzaf.com
License: MIT
Platform: UNKNOWN
